[
    {
        "itemsPrice": 315,
        "taxPrice": 0.14,
        "shippingPrice": 25,
        "totalPrice": 27.89,
        "orderItems": [
            {
                "product": "604e3e26c946be1a14424d5e",
                "name": "Wrogn t-shirt",
                "price": 315,
                "image": "https://res.cloudinary.com/shopit/image/upload/v1606231282/products/tzfsnrli3szrdnb4jgge.jpg",
                "quantity": 1
            }
        ],
        "shippingInfo": {
            "address": "60 Humor Street",
            "city": "Vaghan",
            "phoneNo": 1234567890,
            "postalCode": "M2P 4R2",
            "country": "Canada"
        },
        "paymentInfo": {
            "id": "ri_HnJG23Gvd6Mt8E1vtIOtsNia",
            "status": "succeeded"
        }
    }
]